[
  {
    "id": 1,
    "name": "Toyota Camry New",
    "model": "3.5 D3 PowerPulse Momentum",
    "price": "$40,000",
    "image": "assets/car1.png",
    "fuel": "Petrol",
    "fuelIcon": "assets/petrol.svg",
    "mileage": "100 Miles",
    "mileageIcon": "assets/speedometer.svg",
    "engineType": "Automatic",
    "engineTypeIcon": "assets/gear.svg"
  },
  {
    "id": 2,
    "name": "Honda Accord LX",
    "model": "2.0 Turbo Executive",
    "price": "$38,500",
    "image": "assets/car2.png",
    "fuel": "Petrol",
    "fuelIcon": "assets/petrol.svg",
    "mileage": "90 Miles",
    "mileageIcon": "assets/speedometer.svg",
    "engineType": "Manual",
    "engineTypeIcon": "assets/gear.svg"
  },
  {
    "id": 3,
    "name": "BMW 3 Series",
    "model": "330i M Sport",
    "price": "$45,000",
    "image": "assets/car3.png",
    "fuel": "Petrol",
    "fuelIcon": "assets/petrol.svg",
    "mileage": "95 Miles",
    "mileageIcon": "assets/speedometer.svg",
    "engineType": "Automatic",
    "engineTypeIcon": "assets/gear.svg"
  },
  {
    "id": 4,
    "name": "Audi A4",
    "model": "Premium Plus",
    "price": "$42,000",
    "image": "assets/car4.png",
    "fuel": "Petrol",
    "fuelIcon": "assets/petrol.svg",
    "mileage": "92 Miles",
    "mileageIcon": "assets/speedometer.svg",
    "engineType": "Manual",
    "engineTypeIcon": "assets/gear.svg"
  },
  {
    "id": 5,
    "name": "Mercedes-Benz C-Class",
    "model": "C 300 AMG Line",
    "price": "$47,000",
    "image": "assets/car5.png",
    "fuel": "Petrol",
    "fuelIcon": "assets/petrol.svg",
    "mileage": "98 Miles",
    "mileageIcon": "assets/speedometer.svg",
    "engineType": "Automatic",
    "engineTypeIcon": "assets/gear.svg"
  },
  {
    "id": 6,
    "name": "Lexus ES 350",
    "model": "F Sport",
    "price": "$41,000",
    "image": "assets/car6.png",
    "fuel": "Petrol",
    "fuelIcon": "assets/petrol.svg",
    "mileage": "97 Miles",
    "mileageIcon": "assets/speedometer.svg",
    "engineType": "Manual",
    "engineTypeIcon": "assets/gear.svg"
  },
  {
    "id": 7,
    "name": "Tesla Model 3",
    "model": "Long Range",
    "price": "$50,000",
    "image": "assets/car7.png",
    "fuel": "Petrol",
    "fuelIcon": "assets/petrol.svg",
    "mileage": "250 Miles",
    "mileageIcon": "assets/speedometer.svg",
    "engineType": "Automatic",
    "engineTypeIcon": "assets/gear.svg"
  },
  {
    "id": 8,
    "name": "Ford Mustang",
    "model": "GT Premium",
    "price": "$55,000",
    "image": "assets/car8.png",
    "fuel": "Petrol",
    "fuelIcon": "assets/petrol.svg",
    "mileage": "88 Miles",
    "mileageIcon": "assets/speedometer.svg",
    "engineType": "Manual",
    "engineTypeIcon": "assets/gear.svg"
  },
  {
    "id": 9,
    "name": "Chevrolet Camaro",
    "model": "SS",
    "price": "$53,000",
    "image": "assets/car9.png",
    "fuel": "Petrol",
    "fuelIcon": "assets/petrol.svg",
    "mileage": "85 Miles",
    "mileageIcon": "assets/speedometer.svg",
    "engineType": "Automatic",
    "engineTypeIcon": "assets/gear.svg"
  },
  {
    "id": 10,
    "name": "Nissan Altima",
    "model": "SR",
    "price": "$35,000",
    "image": "assets/car7.png",
    "fuel": "Petrol",
    "fuelIcon": "assets/petrol.svg",
    "mileage": "89 Miles",
    "mileageIcon": "assets/speedometer.svg",
    "engineType": "Manual",
    "engineTypeIcon": "assets/gear.svg"
  },
  {
    "id": 11,
    "name": "Hyundai Sonata",
    "model": "Limited",
    "price": "$33,000",
    "image": "assets/car6.png",
    "fuel": "Petrol",
    "fuelIcon": "assets/petrol.svg",
    "mileage": "93 Miles",
    "mileageIcon": "assets/speedometer.svg",
    "engineType": "Automatic",
    "engineTypeIcon": "assets/gear.svg"
  },
  {
    "id": 12,
    "name": "Kia Optima",
    "model": "EX",
    "price": "$31,000",
    "image": "assets/car5.png",
    "fuel": "Petrol",
    "fuelIcon": "assets/petrol.svg",
    "mileage": "87 Miles",
    "mileageIcon": "assets/speedometer.svg",
    "engineType": "Manual",
    "engineTypeIcon": "assets/gear.svg"
  },
  {
    "id": 13,
    "name": "Volkswagen Passat",
    "model": "SEL",
    "price": "$37,000",
    "image": "assets/car4.png",
    "fuel": "Petrol",
    "fuelIcon": "assets/petrol.svg",
    "mileage": "91 Miles",
    "mileageIcon": "assets/speedometer.svg",
    "engineType": "Automatic",
    "engineTypeIcon": "assets/gear.svg"
  },
  {
    "id": 14,
    "name": "Subaru Legacy",
    "model": "Limited",
    "price": "$36,000",
    "image": "assets/car3.png",
    "fuel": "Petrol",
    "fuelIcon": "assets/petrol.svg",
    "mileage": "86 Miles",
    "mileageIcon": "assets/speedometer.svg",
    "engineType": "Manual",
    "engineTypeIcon": "assets/gear.svg"
  },
  {
    "id": 15,
    "name": "Mazda6",
    "model": "Grand Touring",
    "price": "$34,000",
    "image": "assets/car2.png",
    "fuel": "Petrol",
    "fuelIcon": "assets/petrol.svg",
    "mileage": "96 Miles",
    "mileageIcon": "assets/speedometer.svg",
    "engineType": "Automatic",
    "engineTypeIcon": "assets/gear.svg"
  },
  {
    "id": 16,
    "name": "Volvo S60",
    "model": "R-Design",
    "price": "$46,000",
    "image": "assets/car1.png",
    "fuel": "Petrol",
    "fuelIcon": "assets/petrol.svg",
    "mileage": "94 Miles",
    "mileageIcon": "assets/speedometer.svg",
    "engineType": "Manual",
    "engineTypeIcon": "assets/gear.svg"
  }
]
